lakehut/__init__.py
lakehut-0.0.2.dev1.dist-info/METADATA
lakehut-0.0.2.dev1.dist-info/WHEEL
lakehut-0.0.2.dev1.dist-info/RECORD
