Metadata-Version: 2.3
Name: lakehut
Version: 0.0.2.dev1
Summary: Lakehouse SDK
Project-URL: homepage, https://pypi.org/project/lakehut/
Author-email: Jan Schäfer <jan@schae.fr>
Maintainer-email: Jan Schäfer <jan@schae.fr>
Requires-Python: >=3.11
